LICENSE
MANIFEST.in
README
setup.py
potato/__init__.py
potato/identification.py
potato.egg-info/PKG-INFO
potato.egg-info/SOURCES.txt
potato.egg-info/dependency_links.txt
potato.egg-info/requires.txt
potato.egg-info/top_level.txt
potato/interface/__init__.py
potato/interface/base/__init__.py
potato/interface/base/verify.py
potato/interface/user/__init__.py
potato/interface/user/accessor.py