Metadata-Version: 1.0
Name: potato
Version: 0.0.2
Summary: a dynamic class loader
Home-page: https://github.com/seanochoa/potato
Author: Sean Ochoa
Author-email: sean.m.ochoa@gmail.com
License: Eclipse Public License -v 1.0
Keywords: dynamic class loading
Platform: UNKNOWN
Classifier: Programming Language :: Python
Classifier: Programming Language :: Python :: 2.6
Classifier: Intended Audience :: Developers
Classifier: License :: OSI Approved
Classifier: Operating System :: OS Independent
